{
  "number": "112",
  "name": "坦克兽",
  "cost": "6",
  "race": "资料",
  "skill": "高压加农炮 敌方单体物理火属性威力200 硬直一回合(奈米机械破坏II 命中填充 晕眩冲击)",
  "level": {
    "index": 4,
    "name": "成熟期"
  },
  "preItem": [
    {
      "name": "亚古兽(黑)",
      "number": "019"
    },
    {
      "name": "穿山兽",
      "number": "021"
    },
    {
      "name": "矿石兽",
      "number": "032"
    }
  ],
  "nextItem": [
    {
      "name": "安杜路兽",
      "number": "144"
    },
    {
      "name": "千兆龙兽",
      "number": "156"
    },
    {
      "name": "炮蜂兽",
      "number": "158"
    },
    {
      "name": "骑士兽",
      "number": "182"
    },
    {
      "name": "火山兽",
      "number": "196"
    }
  ],
  "intro": "拥有坦克外形的改造型数码宝贝。"
}