{
  "number": "145",
  "name": "陨石兽",
  "cost": "12",
  "race": "资料",
  "skill": "宇宙闪光 敌方全体魔法无属性威力75(地牛翻身I 流星坠落I 雄伟巨石III 力量能源III)",
  "level": "完全体",
  "preItem": [
    {
      "name": "冰石兽",
      "number": "066"
    },
    {
      "name": "战甲兽",
      "number": "070"
    },
    {
      "name": "岩石兽",
      "number": "099"
    },
    {
      "name": "泥熊兽",
      "number": "113"
    },
    {
      "name": "亚伯兽",
      "number": "120"
    }
  ],
  "nextItem": [
    {
      "name": "外星兽",
      "number": "221"
    },
    {
      "name": "钢铁悟空兽",
      "number": "296"
    },
    {
      "name": "狄安娜兽",
      "number": "259"
    }
  ],
  "intro": "因不明原因以矿石兽体内的矿石资料中的 陨石资料所构成的数码宝贝。 由仅存在于宇宙间的坚硬物质所构成， 具有强劲的防絮力。 必杀技是发射浩瀚宇宙中的神秘能量波的 oQ 『宇宙闪光。。"
}