{
  "number": "228",
  "name": "战斗暴龙兽",
  "cost": "20",
  "race": "疫苗",
  "skill": "盖亚能量炮 敌方全体物理火属性威力90 30%自身ATK+20%    神圣龙卷风 敌方单体无属性高威力DEF贯穿攻击 (流星坠落II 云雾汽油弹III 攻击填充力场 重度强袭 流星坠落III)",
  "level": {
    "index": 5,
    "name": "究极体"
  },
  "preItem": [
    {
      "name": "豆豆兽",
      "number": "199"
    },
    {
      "name": "机械暴龙兽",
      "number": "203"
    },
    {
      "name": "机械暴龙兽(蓝)",
      "number": "204"
    }
  ],
  "nextItem": [
    {
      "name": "奥米加兽",
      "number": "315"
    }
  ],
  "intro": "全身以超金属「数码合金」製的甲包覆的 最强龙战士·暴龙兽系数码宝贝的究极型态。 虽然是和暴龙兽系数码宝贝 巨大身躯不同的人型型态· 但速度、力量皆有飞跃性的提升。 装备于双手上的「龙兽剋星」 虽然能在龙兽系数码宝贝上发挥偌大的威力， 但同时也是会将自己曝露于危险中的双刃剑。 此外·当与背上的外壳合而为时· 就会变成硬度最强的盾「勇气之盾」。"
}