{
  "number": "256",
  "name": "虎蜂兽",
  "cost": "18",
  "race": "病毒",
  "skill": "马赫刺针V  敌方单体物理雷属性威力20 攻击6次 易暴击(奈米机械破坏III 速度填充力场 新月之叶III 反射镜 闪电坠击III)",
  "level": {
    "index": 5,
    "name": "究极体"
  },
  "preItem": [
    {
      "name": "安杜路兽",
      "number": "144"
    },
    {
      "name": "炮蜂兽",
      "number": "158"
    },
    {
      "name": "黄金剑士兽",
      "number": "161"
    },
    {
      "name": "杜兰兽",
      "number": "178"
    },
    {
      "name": "拉比兽",
      "number": "211"
    }
  ],
  "nextItem": [
    {
      "name": "无法继续进化",
      "number": -1
    }
  ],
  "intro": "守护神秘的空中秘密基地 “皇家基地”的改造型数码宝贝。 从虎蜂兽纤细的外表难以想像出 它拥有惊人的体力·战斗中绝不会停止移动。 其中只有顶尖的0.08%菁英才能成为 “秘密部队「皇家突击队」”的员·并能拥有 自己的代号。其单打独斗时的超群战斗能力· 让它拥有“老虎”的代号。 它能够将秘密武器「皇家征服」 如同老虎的獠牙般以二刀流操作。"
}