{
  "number": "260",
  "name": "超恶魔兽",
  "cost": "20",
  "race": "自由",
  "skill": "大灾难  敌方单体物理火属性威力80 攻击3次 硬直一回合(破坏加农III 死亡召唤 马赫突击II 守备破坏力场 流星坠落III)",
  "level": {
    "index": 5,
    "name": "究极体"
  },
  "preItem": [
    {
      "name": "玉兔兽",
      "number": "143"
    },
    {
      "name": "地狱使者兽",
      "number": "146"
    },
    {
      "name": "大古加兽",
      "number": "153"
    },
    {
      "name": "丧尸撒旦兽",
      "number": "169"
    },
    {
      "name": "阿卡迪兽完全体",
      "number": "142"
    }
  ],
  "nextItem": [
    {
      "name": "灭世魔兽",
      "number": "310"
    }
  ],
  "intro": "藉由吸收网路上的资料不断进化和巨大化， 在电脑世界中做尽破坏之能事。"
}